pseudo_runner/__init__.py
pseudo_runner/cli.py
pseudo_runner/config.py
pseudo_runner/converter.py
pseudo_runner/runner.py
pseudo_runner-0.1.dist-info/METADATA
pseudo_runner-0.1.dist-info/WHEEL
pseudo_runner-0.1.dist-info/entry_points.txt
pseudo_runner-0.1.dist-info/top_level.txt
pseudo_runner-0.1.dist-info/RECORD
