Metadata-Version: 2.1
Name: pseudo-runner
Version: 0.1
Summary: A tool to convert pseudocode to Python and execute it.
Home-page: https://github.com/mrkrishnaaggarwal/pseudo-runner
Author: Krishna Aggarwal
Author-email: your-email@example.com
License: MIT
Classifier: Programming Language :: Python :: 3
Classifier: License :: OSI Approved :: MIT License
Classifier: Operating System :: OS Independent
Requires-Python: >=3.7
Requires-Dist: google-generativeai
Requires-Dist: python-dotenv
